setup.py
cym_minimal_package.egg-info/PKG-INFO
cym_minimal_package.egg-info/SOURCES.txt
cym_minimal_package.egg-info/dependency_links.txt
cym_minimal_package.egg-info/requires.txt
cym_minimal_package.egg-info/top_level.txt
my_minimal_package/__init__.py
my_minimal_package/module.py