Metadata-Version: 2.1
Name: cym-minimal-package
Version: 0.1
Summary: Cym's minimal Python package
Author: Aco
